biocarta/__init__.py
biocarta/enrichment.py
biocarta/quantification.py
biocarta/special.py
biocarta-0.2.26.dist-info/LICENSE
biocarta-0.2.26.dist-info/METADATA
biocarta-0.2.26.dist-info/WHEEL
biocarta-0.2.26.dist-info/top_level.txt
biocarta-0.2.26.dist-info/RECORD
