Metadata-Version: 2.1
Name: biocarta
Version: 0.2.26
Summary: UNKNOWN
Home-page: https://github.com/rictjo/biocarta
Author: Richard Tjörnhammar
Author-email: richard.tjornhammar@gmail.com
License: UNKNOWN
Platform: UNKNOWN
Classifier: Programming Language :: Python :: 3.9
Classifier: License :: OSI Approved :: Apache Software License
Classifier: Operating System :: OS Independent
License-File: LICENSE
